{
    "@class": "com.kony.gen.viz.model.component.KVizUserWidget",
    "DNDConfig": null,
    "_children_": [],
    "_height_": {
        "type": "string",
        "value": "100%"
    },
    "_left_": {
        "type": "string",
        "value": "0dp"
    },
    "_margin_": [
        0,
        0,
        0,
        0
    ],
    "_orientation_": 1,
    "_padding_": [
        0,
        0,
        0,
        0
    ],
    "_percent_": true,
    "_skin_": "s0fdc032274b46f4934460e2b74b9da9",
    "_top_": {
        "type": "string",
        "value": "0dp"
    },
    "_width_": {
        "type": "string",
        "value": "100%"
    },
    "canUpdateUI": true,
    "centerx": {
        "type": "string",
        "value": "50%"
    },
    "centery": {
        "type": "string",
        "value": "50%"
    },
    "containerweight": 0,
    "data": {},
    "id": "cmpHallOfFame",
    "info": null,
    "iscustomlayout": false,
    "isvisible": false,
    "kuid": "ab7ad2b2180f405cbf6b83ede752be7e",
    "masterType": 1,
    "name": "kony.ui.UserWidgetInstance",
    "parent": "frmMain",
    "pf": "frmMain",
    "retaincontentalignment": false,
    "retainflexpositionproperties": false,
    "retainflowhorizontalalignment": false,
    "sourceUserWidget": "fb3c68d05aae48c68fe36d7a8765fa90",
    "wType": "UserWidgetInstance",
    "zindex": 1
}